[{"left":43,"top":365,"width":"1150px","height":"475px","content":"Wp-admin post editor, Featured image standard field<br>"},{"left":522,"top":863,"width":"658px","height":"1058px","content":"Wp-admin post editor, post-content standard field<br>"},{"left":446,"top":552,"width":"65px","height":"121px","content":"Coded in the CSS<br>"},{"left":42,"top":242,"width":"1143px","height":"49px","content":"Defined by Wp-admin post editor \"title\" standard field<br>"},{"left":42,"top":304,"width":"1145px","height":"56px","content":"<div>Defined automatically by the post author<br></div>"},{"left":42,"top":144,"width":"1139px","height":"59px","content":"Hard-coded at ./Aole2019/single.php<br>"},{"left":42,"top":2017,"width":"1143px","height":"134px","content":"Automatically set to wordpress standard previous and next posts<br>"}]